{"title":"Minister of State for Vulnerable Children and Families","public_updated_at":"2016-08-09T11:27:56Z","details":{},"routes":[{"path":"/government/ministers/minister-of-state-for-vulnerable-children-and-families","type":"exact"}],"redirects":[],"publishing_app":"whitehall","rendering_app":"whitehall-frontend","need_ids":[],"phase":"live","analytics_identifier":null,"document_type":"ministerial_role","schema_name":"placeholder","first_published_at":"2016-08-08T18:05:29Z","base_path":"/government/ministers/minister-of-state-for-vulnerable-children-and-families","description":null,"content_id":"67abf50e-d0e7-44c9-bdff-1d058a6dde0d","locale":"en","expanded_links":{"organisations":[{"analytics_identifier":"D6","api_path":"/api/content/government/organisations/department-for-education","base_path":"/government/organisations/department-for-education","content_id":"ebd15ade-73b2-4eaf-b1c3-43034a42eb37","description":null,"document_type":"organisation","locale":"en","public_updated_at":"2016-09-23T09:06:42Z","schema_name":"placeholder","title":"Department for Education","withdrawn":false,"details":{"brand":"department-for-education","logo":{"formatted_title":"Department <br/>for Education","crest":"single-identity"}},"links":{}}],"available_translations":[{"title":"Minister of State for Vulnerable Children and Families","public_updated_at":"2016-09-29T11:07:10Z","analytics_identifier":null,"document_type":"ministerial_role","schema_name":"placeholder","base_path":"/government/ministers/minister-of-state-for-vulnerable-children-and-families","description":null,"api_path":"/api/content/government/ministers/minister-of-state-for-vulnerable-children-and-families","withdrawn":false,"content_id":"67abf50e-d0e7-44c9-bdff-1d058a6dde0d","locale":"en"}]},"format":"placeholder","navigation_document_supertype":"other","user_journey_document_supertype":"thing","email_document_supertype":"other","government_document_supertype":"other","payload_version":0}