{"title":"Public sector land use","public_updated_at":"2015-08-11T14:45:24Z","details":{"groups":[],"internal_name":"Planning and development / Public sector land use","beta":true},"routes":[{"path":"/topic/planning-development/public-sector-land-use","type":"exact"},{"path":"/topic/planning-development/public-sector-land-use/latest","type":"exact"},{"path":"/topic/planning-development/public-sector-land-use/email-signup","type":"exact"}],"redirects":[],"publishing_app":"collections-publisher","rendering_app":"collections","need_ids":[],"phase":"beta","analytics_identifier":null,"document_type":"topic","schema_name":"topic","first_published_at":"2016-02-29T09:24:10Z","base_path":"/topic/planning-development/public-sector-land-use","description":"List of information about Public sector land use.","content_id":"206ac299-441d-4ad2-8584-35aa3d019e6c","locale":"en","expanded_links":{"children":[{"analytics_identifier":null,"api_path":"/api/content/guidance/public-request-to-order-disposal-land-owners-cover-letter-and-questionnaire","base_path":"/guidance/public-request-to-order-disposal-land-owners-cover-letter-and-questionnaire","content_id":"5c7edc7f-7631-11e4-a3cb-005056011aef","description":"This letter and questionnaire is sent to land owners once a Public Request to Order Disposal request has been received.","document_type":"detailed_guide","locale":"en","public_updated_at":"2012-11-14T20:15:00Z","schema_name":"detailed_guide","title":"Public Request to Order Disposal: land owner's cover letter and questionnaire","withdrawn":false,"links":{"parent":[{"analytics_identifier":null,"api_path":"/api/content/topic/planning-development/public-sector-land-use","base_path":"/topic/planning-development/public-sector-land-use","content_id":"206ac299-441d-4ad2-8584-35aa3d019e6c","description":"List of information about Public sector land use.","document_type":"topic","locale":"en","public_updated_at":"2015-08-11T14:45:24Z","schema_name":"topic","title":"Public sector land use","withdrawn":false,"links":{}}]}},{"analytics_identifier":null,"api_path":"/api/content/guidance/school-land-and-property-protection-transfer-and-disposal","base_path":"/guidance/school-land-and-property-protection-transfer-and-disposal","content_id":"5f113fd9-7631-11e4-a3cb-005056011aef","description":"Information and guidance about the protection of school playing fields and disposal of assets.","document_type":"detailed_guide","locale":"en","public_updated_at":"2015-02-17T08:53:33Z","schema_name":"detailed_guide","title":"School land and property: protection, transfer and disposal","withdrawn":false,"links":{"parent":[{"analytics_identifier":null,"api_path":"/api/content/topic/planning-development/public-sector-land-use","base_path":"/topic/planning-development/public-sector-land-use","content_id":"206ac299-441d-4ad2-8584-35aa3d019e6c","description":"List of information about Public sector land use.","document_type":"topic","locale":"en","public_updated_at":"2015-08-11T14:45:24Z","schema_name":"topic","title":"Public sector land use","withdrawn":false,"links":{}}]}}],"topic_content":[{"analytics_identifier":null,"api_path":"/api/content/guidance/public-request-to-order-disposal-land-owners-cover-letter-and-questionnaire","base_path":"/guidance/public-request-to-order-disposal-land-owners-cover-letter-and-questionnaire","content_id":"5c7edc7f-7631-11e4-a3cb-005056011aef","description":"This letter and questionnaire is sent to land owners once a Public Request to Order Disposal request has been received.","document_type":"detailed_guide","locale":"en","public_updated_at":"2012-11-14T20:15:00Z","schema_name":"detailed_guide","title":"Public Request to Order Disposal: land owner's cover letter and questionnaire","withdrawn":false,"links":{"topics":[{"analytics_identifier":null,"api_path":"/api/content/topic/planning-development/public-sector-land-use","base_path":"/topic/planning-development/public-sector-land-use","content_id":"206ac299-441d-4ad2-8584-35aa3d019e6c","description":"List of information about Public sector land use.","document_type":"topic","locale":"en","public_updated_at":"2015-08-11T14:45:24Z","schema_name":"topic","title":"Public sector land use","withdrawn":false,"links":{}}]}},{"analytics_identifier":null,"api_path":"/api/content/guidance/school-land-and-property-protection-transfer-and-disposal","base_path":"/guidance/school-land-and-property-protection-transfer-and-disposal","content_id":"5f113fd9-7631-11e4-a3cb-005056011aef","description":"Information and guidance about the protection of school playing fields and disposal of assets.","document_type":"detailed_guide","locale":"en","public_updated_at":"2015-02-17T08:53:33Z","schema_name":"detailed_guide","title":"School land and property: protection, transfer and disposal","withdrawn":false,"links":{"topics":[{"analytics_identifier":null,"api_path":"/api/content/topic/planning-development/public-sector-land-use","base_path":"/topic/planning-development/public-sector-land-use","content_id":"206ac299-441d-4ad2-8584-35aa3d019e6c","description":"List of information about Public sector land use.","document_type":"topic","locale":"en","public_updated_at":"2015-08-11T14:45:24Z","schema_name":"topic","title":"Public sector land use","withdrawn":false,"links":{}}]}}],"parent":[{"analytics_identifier":null,"api_path":"/api/content/topic/planning-development","base_path":"/topic/planning-development","content_id":"8663190a-ee93-4c0a-847e-c39aa9af01ee","description":"List of information about Planning and development.","document_type":"topic","locale":"en","public_updated_at":"2015-08-11T14:45:10Z","schema_name":"topic","title":"Planning and development","withdrawn":false,"links":{}}],"available_translations":[{"title":"Public sector land use","public_updated_at":"2015-08-11T14:45:24Z","analytics_identifier":null,"document_type":"topic","schema_name":"topic","base_path":"/topic/planning-development/public-sector-land-use","description":"List of information about Public sector land use.","api_path":"/api/content/topic/planning-development/public-sector-land-use","withdrawn":false,"content_id":"206ac299-441d-4ad2-8584-35aa3d019e6c","locale":"en"}]},"format":"topic","navigation_document_supertype":"other","user_journey_document_supertype":"finding","email_document_supertype":"other","government_document_supertype":"other","payload_version":0}