{"title":"Marketing & Events Enquiries","public_updated_at":"2016-07-27T13:09:42Z","details":{"description":"","contact_type":"Media contact","title":"Marketing & Events Enquiries","post_addresses":[{"title":"","street_address":"British Consulate General","locality":"Milan","postal_code":"Via San Paolo 7, 20121","world_location":"UK and Italy"}],"email_addresses":[{"title":"","email":"communicationsmilan@fco.gov.uk"}],"phone_numbers":[{"title":"Direct line","number":"+39 02 7230 0253/0249"}]},"routes":[],"redirects":[],"publishing_app":"whitehall","rendering_app":"government-frontend","need_ids":[],"phase":"live","analytics_identifier":null,"document_type":"contact","schema_name":"contact","first_published_at":"2016-07-27T13:09:42Z","base_path":null,"description":null,"content_id":"a29ee1d0-792a-4909-80e4-da60f4596d9e","locale":"en","expanded_links":{"organisations":[{"analytics_identifier":null,"api_path":null,"base_path":null,"content_id":"a29ee1d0-792a-4909-80e4-da60f4596d9e","description":null,"document_type":"contact","locale":"en","public_updated_at":"2016-07-27T13:09:42Z","schema_name":"contact","title":"Marketing & Events Enquiries","withdrawn":false,"links":{}}],"world_locations":[{"analytics_identifier":"WL67","api_path":"/api/content/government/world/italy","base_path":"/government/world/italy","content_id":"5e9f0730-7706-11e4-a3cb-005056011aef","description":null,"document_type":"world_location","locale":"en","public_updated_at":"2013-10-28T14:55:30Z","schema_name":"placeholder","title":"Italy","withdrawn":false,"links":{}}],"available_translations":[{"title":"Marketing and events enquiries, Department for International Trade Italy","public_updated_at":"2016-08-25T14:11:07Z","analytics_identifier":null,"document_type":"contact","schema_name":"contact","base_path":null,"description":null,"api_path":null,"withdrawn":false,"content_id":"a29ee1d0-792a-4909-80e4-da60f4596d9e","locale":"en"}]},"format":"contact","navigation_document_supertype":"guidance","user_journey_document_supertype":"thing","email_document_supertype":"other","government_document_supertype":"other","payload_version":0}