{"title":"Department for International Trade (DIT) Vancouver","public_updated_at":"2016-08-09T09:23:04Z","details":{"description":"","contact_type":"General contact","title":"Department for International Trade (DIT) Vancouver","post_addresses":[{"title":"","street_address":"1111 Melville Street, Suite 800","locality":"Vancouver","postal_code":"V6E 3V6","world_location":"UK and Canada"}],"email_addresses":[{"title":"","email":""}],"phone_numbers":[{"title":"Investment enquiries","number":"+1 604 683 4421 extension 2211"},{"title":"Trade enquiries","number":"+1 604 683 4421 extension 2210"}]},"routes":[],"redirects":[],"publishing_app":"whitehall","rendering_app":"government-frontend","need_ids":[],"phase":"live","analytics_identifier":null,"document_type":"contact","schema_name":"contact","first_published_at":"2016-08-09T09:23:05Z","base_path":null,"description":null,"content_id":"9348c500-eaef-421d-9c5c-1602e9b033f7","locale":"en","expanded_links":{"organisations":[{"analytics_identifier":null,"api_path":null,"base_path":null,"content_id":"9348c500-eaef-421d-9c5c-1602e9b033f7","description":null,"document_type":"contact","locale":"en","public_updated_at":"2016-08-09T09:23:04Z","schema_name":"contact","title":"Department for International Trade (DIT) Vancouver","withdrawn":false,"links":{}}],"world_locations":[{"analytics_identifier":"WL28","api_path":"/api/content/government/world/canada","base_path":"/government/world/canada","content_id":"5e9ee897-7706-11e4-a3cb-005056011aef","description":null,"document_type":"world_location","locale":"en","public_updated_at":"2015-05-13T14:41:25Z","schema_name":"placeholder","title":"Canada","withdrawn":false,"links":{}}],"available_translations":[{"title":"Department for International Trade (DIT) Vancouver","public_updated_at":"2016-08-09T09:23:04Z","analytics_identifier":null,"document_type":"contact","schema_name":"contact","base_path":null,"description":null,"api_path":null,"withdrawn":false,"content_id":"9348c500-eaef-421d-9c5c-1602e9b033f7","locale":"en"}]},"format":"contact","navigation_document_supertype":"guidance","user_journey_document_supertype":"thing","email_document_supertype":"other","government_document_supertype":"other","payload_version":0}